[{"word": "1 of 2", "bounding_box": [1259, 47, 1301, 65]}, {"word": "Page", "bounding_box": [1181, 48, 1219, 68]}, {"word": "04/27/2013", "bounding_box": [1277, 73, 1359, 91]}, {"word": "4.30AM", "bounding_box": [1395, 73, 1459, 91]}, {"word": "Order Confirmation", "bounding_box": [733, 75, 869, 91]}, {"word": "Printed:", "bounding_box": [1183, 75, 1239, 91]}, {"word": "5407135", "bounding_box": [963, 187, 1027, 205]}, {"word": "0089364317", "bounding_box": [1350, 188, 1438, 204]}, {"word": "Advertiser No:", "bounding_box": [803, 189, 905, 205]}, {"word": "Order No:", "bounding_box": [1183, 189, 1255, 205]}, {"word": "Start Date:", "bounding_box": [801, 230, 877, 249]}, {"word": "Co-op:", "bounding_box": [1182, 230, 1233, 251]}, {"word": "08/14/2002", "bounding_box": [965, 231, 1045, 247]}, {"word": "No", "bounding_box": [1353, 231, 1377, 247]}, {"word": "02/05/2019", "bounding_box": [963, 265, 1045, 285]}, {"word": "Package:", "bounding_box": [1181, 265, 1248, 289]}, {"word": "End Date:", "bounding_box": [803, 269, 873, 285]}, {"word": "No", "bounding_box": [1353, 269, 1375, 285]}, {"word": "Agency Comm::", "bounding_box": [1180, 298, 1298, 322]}, {"word": "Month Type:", "bounding_box": [801, 299, 891, 319]}, {"word": "Broadcast", "bounding_box": [965, 301, 1035, 317]}, {"word": "969", "bounding_box": [1351, 301, 1385, 317]}, {"word": "Revision #:", "bounding_box": [801, 341, 881, 357]}, {"word": "DMSE-SURPYNZXMAZKCIJ", "bounding_box": [963, 371, 1177, 389]}, {"word": "CPE:", "bounding_box": [801, 373, 841, 389]}, {"word": "PHILADELPHIA, MMS", "bounding_box": [965, 411, 1135, 429]}, {"word": "AE:", "bounding_box": [803, 413, 833, 429]}, {"word": "12/14/2021 01:44 PM by Fusion", "bounding_box": [962, 444, 1186, 468]}, {"word": "Entered:", "bounding_box": [801, 447, 863, 465]}, {"word": "12/14/2021 03.02 PM by ccrhunlc", "bounding_box": [962, 476, 1202, 500]}, {"word": "Last Update:", "bounding_box": [799, 478, 891, 497]}, {"word": "Candyce Parrish", "bounding_box": [169, 479, 283, 497]}, {"word": "1129 Lamson Path", "bounding_box": [167, 495, 297, 513]}, {"word": "22024,Costa Mesa", "bounding_box": [167, 513, 301, 533]}, {"word": "WKEE-FM 35551816 AFPI PI 12151219 Political Issue", "bounding_box": [963, 517, 1345, 537]}, {"word": "Note:", "bounding_box": [800, 518, 843, 537]}, {"word": "United States", "bounding_box": [169, 533, 263, 551]}, {"word": "Note 2:", "bounding_box": [801, 557, 855, 575]}, {"word": "Spl Req Inv:", "bounding_box": [798, 590, 890, 614]}, {"word": "lskip W:", "bounding_box": [836, 773, 900, 798]}, {"word": "[Bind To", "bounding_box": [267, 775, 329, 795]}, {"word": "EEnd Date", "bounding_box": [393, 775, 465, 795]}, {"word": "No Of Weeks", "bounding_box": [541, 775, 635, 795]}, {"word": "lord Cost", "bounding_box": [1397, 775, 1469, 795]}, {"word": "Market Station", "bounding_box": [93, 777, 205, 795]}, {"word": "Rate Type", "bounding_box": [701, 777, 777, 797]}, {"word": "Spots/ W:", "bounding_box": [965, 777, 1035, 797]}, {"word": "Spot Length", "bounding_box": [1101, 777, 1191, 797]}, {"word": "Ord Spots", "bounding_box": [1257, 777, 1333, 797]}, {"word": "106/25/2000", "bounding_box": [393, 839, 473, 855]}, {"word": "6.41", "bounding_box": [701, 839, 731, 855]}, {"word": "H5S.11", "bounding_box": [1397, 839, 1447, 855]}, {"word": "Il11/22/2010", "bounding_box": [387, 855, 473, 875]}, {"word": "1l5o794", "bounding_box": [531, 855, 583, 875]}, {"word": "150794", "bounding_box": [963, 855, 1011, 875]}, {"word": "1l5o794", "bounding_box": [1249, 855, 1301, 875]}, {"word": "Il1o15.88", "bounding_box": [1391, 855, 1455, 875]}, {"word": "Io.02", "bounding_box": [695, 859, 733, 875]}, {"word": "1p46.97", "bounding_box": [692, 874, 750, 898]}, {"word": "146.97", "bounding_box": [1390, 874, 1448, 898]}, {"word": "Ilo8/27/2007", "bounding_box": [387, 877, 473, 895]}, {"word": "1l11,28/2002", "bounding_box": [387, 895, 473, 915]}, {"word": "Il254", "bounding_box": [533, 897, 567, 915]}, {"word": "1254", "bounding_box": [1249, 897, 1285, 915]}, {"word": "Il320.04", "bounding_box": [1391, 897, 1447, 915]}, {"word": "1i.26", "bounding_box": [695, 899, 733, 915]}, {"word": "1254", "bounding_box": [961, 899, 993, 915]}, {"word": "No. of Spots Misc/Digital:", "bounding_box": [604, 948, 788, 972]}, {"word": "968043", "bounding_box": [933, 949, 989, 969]}, {"word": "63.7 USD", "bounding_box": [1471, 949, 1541, 969]}, {"word": "Ordered Gross:", "bounding_box": [1143, 953, 1249, 969]}, {"word": "S1576", "bounding_box": [1479, 985, 1527, 1005]}, {"word": "Agency Commission:", "bounding_box": [1143, 987, 1291, 1007]}, {"word": "Net:", "bounding_box": [1198, 1008, 1234, 1031]}, {"word": "S1768.66", "bounding_box": [1469, 1009, 1537, 1029]}, {"word": "Ordered", "bounding_box": [1143, 1013, 1199, 1029]}, {"word": "S2659.2", "bounding_box": [1469, 1035, 1529, 1055]}, {"word": "Total Net Due:", "bounding_box": [1143, 1039, 1245, 1055]}, {"word": "Participating Customers", "bounding_box": [41, 1636, 210, 1662]}, {"word": "America First Policy Institute", "bounding_box": [45, 1673, 245, 1693]}, {"word": "100%", "bounding_box": [605, 1673, 649, 1691]}]