[{"word": "Contract Summary", "bounding_box": [694, 109, 862, 134]}, {"word": "Order", "bounding_box": [1195, 111, 1249, 131]}, {"word": "Rev", "bounding_box": [1351, 111, 1387, 131]}, {"word": "# Wks", "bounding_box": [1421, 111, 1475, 131]}, {"word": "36506", "bounding_box": [1177, 135, 1233, 155]}, {"word": "Advertiser", "bounding_box": [592, 160, 698, 184]}, {"word": "Ereage", "bounding_box": [1474, 162, 1536, 186]}, {"word": "Date", "bounding_box": [1177, 163, 1223, 183]}, {"word": "Start", "bounding_box": [1389, 165, 1441, 183]}, {"word": "er", "bounding_box": [1291, 167, 1313, 183]}, {"word": "Hubbell for", "bounding_box": [594, 180, 708, 204]}, {"word": "01/03/2", "bounding_box": [1178, 180, 1254, 204]}, {"word": "09/04/2", "bounding_box": [1386, 180, 1462, 204]}, {"word": "/06/2", "bounding_box": [1496, 180, 1550, 208]}, {"word": "Governor", "bounding_box": [715, 185, 797, 201]}, {"word": "Thomas Giles", "bounding_box": [71, 207, 195, 227]}, {"word": "Balesperson", "bounding_box": [593, 213, 708, 239]}, {"word": "Time", "bounding_box": [1281, 215, 1323, 233]}, {"word": "7884c072-6755", "bounding_box": [902, 216, 1040, 240]}, {"word": "emos", "bounding_box": [1207, 217, 1249, 231]}, {"word": "1016", "bounding_box": [71, 227, 115, 247]}, {"word": "Rosemont Cove", "bounding_box": [123, 229, 257, 249]}, {"word": "9:20", "bounding_box": [1279, 233, 1323, 253]}, {"word": "Hubbell for", "bounding_box": [898, 234, 1010, 258]}, {"word": "Gov (16223)", "bounding_box": [1014, 234, 1128, 258]}, {"word": "Statenets", "bounding_box": [612, 236, 708, 260]}, {"word": "50725 , Hickory", "bounding_box": [69, 242, 216, 270]}, {"word": "United States", "bounding_box": [71, 267, 205, 287]}, {"word": "gency Phone", "bounding_box": [904, 270, 1020, 294]}, {"word": "Sales Ottice", "bounding_box": [593, 271, 717, 291]}, {"word": "Survey", "bounding_box": [1200, 272, 1261, 291]}, {"word": "88-789-7240", "bounding_box": [905, 289, 1019, 309]}, {"word": "earfield", "bounding_box": [603, 291, 687, 311]}, {"word": "Radio Iowa", "bounding_box": [78, 454, 184, 478]}, {"word": "10,360", "bounding_box": [1080, 454, 1148, 478]}, {"word": "20", "bounding_box": [661, 457, 685, 477]}, {"word": "Haulamatic-0453 NS", "bounding_box": [79, 507, 263, 527]}, {"word": "1155.30", "bounding_box": [1083, 507, 1157, 527]}, {"word": "ACL", "bounding_box": [73, 533, 107, 547]}, {"word": "venicles", "bounding_box": [113, 533, 195, 549]}, {"word": "Total", "bounding_box": [225, 533, 277, 549]}, {"word": "Gross", "bounding_box": [283, 533, 335, 549]}, {"word": "2529.1", "bounding_box": [289, 557, 353, 577]}, {"word": "369", "bounding_box": [1053, 557, 1087, 577]}, {"word": "1485.4", "bounding_box": [1451, 557, 1517, 577]}, {"word": "98", "bounding_box": [1527, 557, 1551, 577]}, {"word": "AlL Vehicles", "bounding_box": [70, 582, 196, 606]}, {"word": "Total Units", "bounding_box": [220, 582, 336, 606]}, {"word": "13", "bounding_box": [311, 607, 335, 625]}, {"word": "52", "bounding_box": [1525, 607, 1549, 625]}, {"word": "$1294", "bounding_box": [997, 630, 1054, 656]}, {"word": "$2084 . 0", "bounding_box": [1427, 630, 1508, 656]}, {"word": "Air Time", "bounding_box": [427, 633, 511, 653]}, {"word": "1155.3 USD", "bounding_box": [557, 633, 663, 653]}, {"word": "Total", "bounding_box": [1277, 633, 1333, 653]}, {"word": "Commission:", "bounding_box": [873, 635, 985, 653]}, {"word": "gency", "bounding_box": [811, 637, 865, 657]}, {"word": "Net:", "bounding_box": [1339, 637, 1381, 653]}, {"word": "Gros", "bounding_box": [429, 655, 471, 671]}, {"word": "Cancellation /Change Clause:", "bounding_box": [124, 731, 408, 758]}, {"word": "at the rate appropriate to the", "bounding_box": [326, 750, 632, 777]}, {"word": "of advertisements booked before such", "bounding_box": [706, 750, 1074, 774]}, {"word": "cancellation becomes effective .", "bounding_box": [1096, 750, 1412, 774]}, {"word": "pay the Broadcaster", "bounding_box": [126, 752, 320, 776]}, {"word": "number", "bounding_box": [637, 755, 701, 773]}, {"word": "Hattiesburg", "bounding_box": [553, 824, 672, 854]}, {"word": "759 San Luis Pass ,", "bounding_box": [294, 828, 478, 852]}, {"word": "54811", "bounding_box": [484, 828, 542, 852]}, {"word": "Lexie Donaldson ,", "bounding_box": [125, 830, 287, 851]}, {"word": "867.368. 1053", "bounding_box": [130, 854, 258, 878]}, {"word": "learfield. com", "bounding_box": [394, 854, 532, 878]}, {"word": "WWW", "bounding_box": [355, 863, 391, 877]}, {"word": "444.854.1495", "bounding_box": [245, 873, 369, 893]}]